{
    "datosPersonales": {
      "nombre": "Samuel Lamas Monje",
      "correoElectronico": "samusada95@gmail.com",
      "telefono": "617300021",
      "direccion": "Tu Dirección, Ciudad, País"
    },

    "sobreMi": {
      "descripcion": "Lorem ipsum dolor sit amet, consectetur adipiscing elit. Sed do eiusmod tempor incididunt ut labore et dolore magna aliqua. Ut enim ad minim veniam, quis nostrud exercitation ullamco laboris nisi ut aliquip ex ea commodo consequat. Duis aute irure dolor in reprehenderit in voluptate velit esse cillum dolore eu fugiat nulla pariatur. Excepteur sint occaecat cupidatat non proident, sunt in culpa qui officia deserunt mollit anim id est laborum."
    },

    "estudios": [
      {
        "nivelTitulo": "FP Superior",
        "titulo": "Animación 3D y Creación de Videojuegos",
        "institucion": "CIFP Imaxe e Son",
        "ubicacion": "A Coruña, España",
        "fechaInicio": "",
        "fechaFin": 2021
      },
      {
        "nivelTitulo": "Certificado Profesional",
        "titulo": "Programación de Sistemas Informáticos",
        "institucion": "Academia ADAMS",
        "ubicacion": "A Coruña, España",
        "fechaInicio": "",
        "fechaFin": 2023
      },
      {
        "nivelTitulo": "Certificado",
        "titulo": "Programación Web - Full Stack",
        "institucion": "HACKABOSS",
        "ubicacion": "A Coruña, España",
        "fechaInicio": "",
        "fechaFin": 2024
      }
    ],

    "conocimientos": [
      {
        "materia": "HTML",
        "nivel": 90
      },
      {
        "materia": "CSS",
        "nivel": 80
      },
      {
        "materia": "JavaScript",
        "nivel": 50
      },
      {
        "materia": "MySQL",
        "nivel": 75
      },
      {
        "materia": "MySQL WorkBench",
        "nivel": 75
      },
      {
        "materia": "DOM",
        "nivel": 100
      },
      {
        "materia": "NODE",
        "nivel": 50
      }
    ],

    "idiomas": [
      {
        "idioma": "Español",
        "nivel": 100
      },
      {
        "idioma": "Inglés",
        "nivel": 50
      }
    ],

    "experienciaLaboral": [
      {
        "puesto": "Camarero",
        "empresa": "Mercado del Puerto",
        "ubicacion": "Sada, España",
        "fechaInicio": "",
        "fechaFin": "2023",
        "responsabilidades": [
          "Camarero en barra",
          "Ayuda en comedor"
        ]
      },
      {
        "puesto": "Mozo de almacén",
        "empresa": "Recambios Barreiro",
        "ubicacion": "Polígono industrial de Bergondo, España",
        "fechaInicio": "",
        "fechaFin": "2021",
        "responsabilidades": [
          "Reparto",
          "Almacén"
        ]
      },
      {
        "puesto": "Repartidor",
        "empresa": "La Biela",
        "ubicacion": "Polígono industrial de Bergondo, España",
        "fechaInicio": "",
        "fechaFin": "2015",
        "responsabilidades": [
          "Reparto",
          "Cocina"
        ]
      }
    ]
  }
  